{
    "provides": {
        "values": {
            "juliet": "String",
            "getBuffer": ["arrow", ["String"], "tany"],
            "makeSound": ["arrow", ["Any", "Any", "Any"],
                ["local", "Sound"]
            ],
            "urlSound": ["arrow", ["String"],
                ["local", "Sound"]
            ],
            "overlay": ["arrow", ["tany"],
                ["local", "Sound"]
            ],
            "playSound": ["arrow", ["tany"], "Any"]
        },
        "datatypes": {
            "Sound": ["data", "Sound", [],
                [], {}
            ]
        },
        "aliases": {}
    }
}